blitzcomp/__init__.py
blitzcomp/parallel.py
datarie/sites.py
datarie/time.py
neoplot/figures.py
neoplot/plots.py
neoplot/fonts/Montserrat-Black.ttf
neoplot/fonts/Montserrat-BlackItalic.ttf
neoplot/fonts/Montserrat-Bold.ttf
neoplot/fonts/Montserrat-BoldItalic.ttf
neoplot/fonts/Montserrat-ExtraBold.ttf
neoplot/fonts/Montserrat-ExtraBoldItalic.ttf
neoplot/fonts/Montserrat-ExtraLight.ttf
neoplot/fonts/Montserrat-ExtraLightItalic.ttf
neoplot/fonts/Montserrat-Italic.ttf
neoplot/fonts/Montserrat-Light.ttf
neoplot/fonts/Montserrat-LightItalic.ttf
neoplot/fonts/Montserrat-Medium.otf
neoplot/fonts/Montserrat-Medium.ttf
neoplot/fonts/Montserrat-MediumItalic.ttf
neoplot/fonts/Montserrat-Regular.ttf
neoplot/fonts/Montserrat-SemiBold.ttf
neoplot/fonts/Montserrat-SemiBoldItalic.ttf
neoplot/fonts/Montserrat-Thin.ttf
neoplot/fonts/Montserrat-ThinItalic.ttf
neoplot/fonts/Montserrat-VariableFont_wght.ttf
sciency/meteorology.py
sciency/units.py
crusty-0.10.6.dist-info/LICENSE
crusty-0.10.6.dist-info/METADATA
crusty-0.10.6.dist-info/WHEEL
crusty-0.10.6.dist-info/top_level.txt
crusty-0.10.6.dist-info/RECORD
