Metadata-Version: 2.1
Name: crusty
Version: 0.10.6
Summary: A convinience python package for HPC computation, science and plotting.
License-File: LICENSE
Requires-Dist: requests
Requires-Dist: pip
Requires-Dist: colorcet
Requires-Dist: numpy==1.26.4
Requires-Dist: pandas
Requires-Dist: matplotlib
Requires-Dist: cartopy
Requires-Dist: mpi4py
Requires-Dist: pyarrow
Requires-Dist: netCDF4
Requires-Dist: xarray
Requires-Dist: scipy
Requires-Dist: pint
Requires-Dist: pint-pandas
Requires-Dist: pint-xarray
Requires-Dist: psutil
Requires-Dist: scikit-learn
Requires-Dist: uncertainties
Requires-Dist: openpyxl
Requires-Dist: pymannkendall
Requires-Dist: plottable
Requires-Dist: importlib-metadata; python_version == "3.11"
